musync/__init__.py
musync/logger.py
musync/main.py
musync/sync.py
musync/models/__init__.py
musync/models/artist.py
musync/models/playlist.py
musync/models/song.py
musync/providers/__init__.py
musync/providers/base.py
musync/providers/spotify.py
musync/providers/youtube.py
pymusync-0.1.0.dist-info/LICENSE
pymusync-0.1.0.dist-info/METADATA
pymusync-0.1.0.dist-info/WHEEL
pymusync-0.1.0.dist-info/entry_points.txt
pymusync-0.1.0.dist-info/top_level.txt
pymusync-0.1.0.dist-info/RECORD
