Metadata-Version: 2.1
Name: pymusync
Version: 0.1.0
Summary: A tool for syncing user data across music streaming services.
Author-email: Rory Devitt <rorytdevitt@gmail.com>
License: Copyright © 2024 Rory Devitt
Requires-Python: >=3.12
License-File: LICENSE
Requires-Dist: loguru>=0.7.2
Requires-Dist: pydantic>=2.9.2
Requires-Dist: python-dotenv>=1.0.1
Requires-Dist: spotipy>=2.24.0
Requires-Dist: typer>=0.13.1
Requires-Dist: ytmusicapi>=1.8.2
